rakeshkannatest/__init__.py
rakeshkannatest/main.py
rakeshkannatest-0.1.0.dist-info/LICENSE
rakeshkannatest-0.1.0.dist-info/METADATA
rakeshkannatest-0.1.0.dist-info/WHEEL
rakeshkannatest-0.1.0.dist-info/top_level.txt
rakeshkannatest-0.1.0.dist-info/RECORD
