Metadata-Version: 2.1
Name: rakeshkannatest
Version: 0.1.0
Summary: My first module
Author: Rakesh Kanna
Author-email: rakeshkanna0108@gmail.com
License: MIT
Keywords: first,module,python
Requires-Python: >=3.6
License-File: LICENSE
